frangle/__init__.py
frangle-0.0.3.dist-info/LICENSE
frangle-0.0.3.dist-info/METADATA
frangle-0.0.3.dist-info/WHEEL
frangle-0.0.3.dist-info/top_level.txt
frangle-0.0.3.dist-info/RECORD
